async_etcd3gw/__init__.py
async_etcd3gw/async_client.py
async_etcd3gw/async_lease.py
async_etcd3gw/async_lock.py
async_etcd3gw/async_watch.py
async_etcd3gw/exceptions.py
async_etcd3gw/utils.py
async_etcd3gw-0.8.dist-info/LICENSE
async_etcd3gw-0.8.dist-info/METADATA
async_etcd3gw-0.8.dist-info/WHEEL
async_etcd3gw-0.8.dist-info/top_level.txt
async_etcd3gw-0.8.dist-info/zip-safe
async_etcd3gw-0.8.dist-info/RECORD
