Metadata-Version: 2.1
Name: async-etcd3gw
Version: 0.8
Summary: An async Python client for etcd3 grpc-gateway v3 API
Home-page: https://github.com/DLBD-Department/async_etcd3gw
Author: Alkemy spa
Author-email: DLBDDepartment@alkemy.com
License: Apache License 2.0
Project-URL: Bug Tracker, https://github.com/DLBD-Department/async_etcd3gw/issues
Project-URL: Source Code, https://github.com/DLBD-Department/async_etcd3gw
Keywords: etcd,asyncio,aiohttp
Platform: any
Classifier: Environment :: Console
Classifier: Intended Audience :: Developers
Classifier: Intended Audience :: Information Technology
Classifier: License :: OSI Approved :: Apache Software License
Classifier: Operating System :: OS Independent
Classifier: Programming Language :: Python
Classifier: Programming Language :: Python :: 3
Classifier: Programming Language :: Python :: 3.9
Classifier: Programming Language :: Python :: 3.10
Classifier: Programming Language :: Python :: 3.11
Classifier: Topic :: System :: Distributed Computing
Requires-Python: >=3.9
License-File: LICENSE
Requires-Dist: aiohttp
Provides-Extra: test
Requires-Dist: pytest ; extra == 'test'
